PheQTK/Quick.py
PheQTK/__init__.py
PheQTK/helpers/__init__.py
PheQTK/helpers/covariate_validation.py
PheQTK/helpers/phecode_validation.py
PheQTK/helpers/regex_patterns.py
PheQTK/helpers/response_validation.py
PheQTK/helpers/variant_validation.py
PheQTK/modules/__init__.py
PheQTK/modules/cohorts/Covariates.py
PheQTK/modules/cohorts/Variant.py
PheQTK/modules/cohorts/__init__.py
PheQTK/modules/cohorts/cohorts.py
PheQTK/modules/phecodes/Phecodes.py
PheQTK/modules/phecodes/__init__.py
PheQTK/modules/phewass/__init__.py
PheQTK/modules/phewass/phewass.py
PheQTK/modules/plots/__init__.py
PheQTK/modules/plots/plots.py
pheqtk-0.0.4.dist-info/licenses/LICENSE
pheqtk-0.0.4.dist-info/METADATA
pheqtk-0.0.4.dist-info/WHEEL
pheqtk-0.0.4.dist-info/top_level.txt
pheqtk-0.0.4.dist-info/RECORD
