Metadata-Version: 2.4
Name: PheQTK
Version: 0.0.4
Summary: A wrapper to the PheTK package.
Author-email: Marjorie Kohn <marjoriekohn@icloud.com>
License-Expression: MIT
Project-URL: Homepage, https://github.com/marjoriekohn/PheQTK
Project-URL: Issues, https://github.com/marjoriekohn/PheQTK/issues
Project-URL: PheTK, https://github.com/nhgritctran/PheTK
Classifier: Programming Language :: Python :: 3
Classifier: Operating System :: OS Independent
Requires-Python: >=3.9
License-File: LICENSE
Requires-Dist: PheTK==0.1.47
Dynamic: license-file
